MANIFEST
MANIFEST.in
NOTES
Num.py
README.txt
__init__.py
axis.py
colors.py
constants.py
die.py
ez_setup.py
forbin.py
pid.py
primitive.py
property.py
setup.py
utility.py
./Num.py
./__init__.py
./axis.py
./colors.py
./constants.py
./die.py
./ez_setup.py
./forbin.py
./pid.py
./primitive.py
./property.py
./utility.py
bin/g_multiplot
bin/g_widthplot
graphite.egg-info/PKG-INFO
graphite.egg-info/SOURCES.txt
graphite.egg-info/dependency_links.txt
graphite.egg-info/requires.txt
graphite.egg-info/top_level.txt
tests/blitter.dat
tests/blittergraph.gif
tests/blittergraph.pdf
tests/blittergraph.py
tests/testa.pdf
tests/testa.py
tests/testb.py