Metadata-Version: 1.0
Name: graphite
Version: 0.71
Summary: Line and scatterplots of data, libraries and command line programs.
Home-page: http://graphite.sourceforge.net
Author: Greg Kochanski
Author-email: gpk@kochanski.org
License: GPL2
Keywords: plot scientific graphics scatterplot 3d 3D 2D 2d xy bar
Platform: All
Classifier: License :: OSI Approved :: GNU General Public License (GPL)
Classifier: Operating System :: OS Independent
Classifier: Development Status :: 4 - Beta
Classifier: Topic :: Scientific/Engineering
Classifier: Environment :: Console
Classifier: Intended Audience :: End Users/Desktop
Classifier: Intended Audience :: Developers
Classifier: Intended Audience :: Science/Research
Classifier: Programming Language :: Python
Classifier: Operating System :: OS Independent
Classifier: Programming Language :: Python
Classifier: Topic :: Scientific/Engineering :: Visualization
